examples/__init__.py
examples/locust.py
load_testing_hub/__init__.py
load_testing_hub/cli/__init__.py
load_testing_hub/cli/main.py
load_testing_hub/cli/commands/__init__.py
load_testing_hub/cli/commands/upload_locust_report.py
load_testing_hub/src/__init__.py
load_testing_hub/src/api/__init__.py
load_testing_hub/src/api/client.py
load_testing_hub/src/api/schema/__init__.py
load_testing_hub/src/api/schema/exception_results.py
load_testing_hub/src/api/schema/load_test_results.py
load_testing_hub/src/api/schema/method_results.py
load_testing_hub/src/api/schema/pipeline.py
load_testing_hub/src/api/schema/ratio_results.py
load_testing_hub/src/api/schema/scenarios.py
load_testing_hub/src/api/schema/services.py
load_testing_hub/src/api/schema/upload.py
load_testing_hub/src/api/schema/metrics/__init__.py
load_testing_hub/src/api/schema/metrics/base.py
load_testing_hub/src/api/schema/metrics/content_length.py
load_testing_hub/src/api/schema/metrics/number_of_requests.py
load_testing_hub/src/api/schema/metrics/number_of_users.py
load_testing_hub/src/api/schema/metrics/percentiles.py
load_testing_hub/src/api/schema/metrics/requests_per_second.py
load_testing_hub/src/api/schema/metrics/response_times.py
load_testing_hub/src/api/schema/results_history/__init__.py
load_testing_hub/src/api/schema/results_history/base.py
load_testing_hub/src/api/schema/results_history/load_test_results_history.py
load_testing_hub/src/api/schema/results_history/method_results_history.py
load_testing_hub/src/providers/__init__.py
load_testing_hub/src/providers/locust/__init__.py
load_testing_hub/src/providers/locust/controllers/__init__.py
load_testing_hub/src/providers/locust/controllers/build.py
load_testing_hub/src/providers/locust/controllers/exception_results.py
load_testing_hub/src/providers/locust/controllers/load_test_results.py
load_testing_hub/src/providers/locust/controllers/method_results.py
load_testing_hub/src/providers/locust/controllers/ratio_results.py
load_testing_hub-0.5.0.dist-info/licenses/LICENSE
load_testing_hub-0.5.0.dist-info/METADATA
load_testing_hub-0.5.0.dist-info/WHEEL
load_testing_hub-0.5.0.dist-info/entry_points.txt
load_testing_hub-0.5.0.dist-info/top_level.txt
load_testing_hub-0.5.0.dist-info/RECORD
