Metadata-Version: 2.4
Name: load-testing-hub
Version: 0.5.0
Summary: Python connector and CLI tool for uploading Locust performance 
Home-page: https://github.com/Nikita-Filonov/load-testing-hub
Author: Nikita Filonov
Author-email: filonov.nikitkaa@gmail.com
Project-URL: Bug Tracker, https://github.com/Nikita-Filonov/load-testing-hub/issues
Classifier: Programming Language :: Python :: 3
Classifier: License :: OSI Approved :: MIT License
Classifier: Operating System :: OS Independent
Requires-Python: >=3.11
License-File: LICENSE
Requires-Dist: click
Requires-Dist: httpx
Requires-Dist: pyyaml>=6.0.2
Requires-Dist: pydantic>=2.0.0
Dynamic: author
Dynamic: author-email
Dynamic: classifier
Dynamic: description
Dynamic: description-content-type
Dynamic: home-page
Dynamic: license-file
Dynamic: project-url
Dynamic: requires-dist
Dynamic: requires-python
Dynamic: summary
